MANIFEST.in
requirements.txt
setup.py
configuration_panda.egg-info/PKG-INFO
configuration_panda.egg-info/SOURCES.txt
configuration_panda.egg-info/dependency_links.txt
configuration_panda.egg-info/requires.txt
configuration_panda.egg-info/top_level.txt
saddlebags/__init__.py
saddlebags/exceptions.py
saddlebags/saddlebag.py
saddlebags/test/__init__.py
saddlebags/test/test_saddlebag.py